[
  {
    "id": "REC-001",
    "fieldName": "Valley View Sector A",
    "variety": "Low Glycemic",
    "country": "IND",
    "vendorName": "AgroCorp India",
    "growerName": "Rajesh Patel",
    "cropSeason": "2026",
    "fieldLocation": "18.5204, 73.8567",
    "region": "AMESA",
    "vendorContact": "+91-9876543210",
    "cipcApplied": "CIPC",
    "activeIngredientRate": "12.50",
    "irrigationType": "Drip",
    "nApplied": "25.21",
    "nTotal": "2.52",
    "pTotal": "1.20",
    "kTotal": "1.80",
    "vrtUsed": "Yes",
    "fertilizerType": "Mineral NPK",
    "fertilizerNature": "Mineral",
    "nitrogenAnalysis": "20.0",
    "ammoniaPercentage": "38.9",
    "nitricPercentage": "30.1",
    "ureaPercentage": "31.0",
    "phosphateAnalysis": "15.0",
    "potassiumAnalysis": "15.0",
    "applicationRate": "150.0",
    "applicationMethod": "Drip",
    "emissionsInhibitors": "Yes",
    "applicationDate": "2026-03-10",
    "agronomistName": "Sujit Kumar",
    "moisturePercentage": "14.2",
    "defectRate": "2.1",
    "yieldTons": "34.5",
    "submissionStatus": "Approved",
    "timestamp": "2026-07-01T10:00:00.000Z"
  },
  {
    "id": "REC-002",
    "fieldName": "Hacienda del Sol",
    "variety": "Atlantic",
    "country": "MEX",
    "vendorName": "Delgado Farms",
    "growerName": "Carlos Delgado",
    "cropSeason": "2026",
    "fieldLocation": "20.6597, -103.3496",
    "region": "LATAM",
    "vendorContact": "+52-555-0192",
    "cipcApplied": "None",
    "activeIngredientRate": "0.00",
    "irrigationType": "Spray",
    "nApplied": "30.50",
    "nTotal": "4.10",
    "pTotal": "2.05",
    "kTotal": "3.20",
    "vrtUsed": "No",
    "fertilizerType": "Organic Compost",
    "fertilizerNature": "Organic",
    "nitrogenAnalysis": "5.0",
    "ammoniaPercentage": "10.0",
    "nitricPercentage": "0.0",
    "ureaPercentage": "90.0",
    "phosphateAnalysis": "3.5",
    "potassiumAnalysis": "6.0",
    "applicationRate": "500.0",
    "applicationMethod": "Broadcast",
    "emissionsInhibitors": "No",
    "applicationDate": "2026-02-15",
    "agronomistName": "Carlos Garcia",
    "moisturePercentage": "18.9",
    "defectRate": "7.4",
    "yieldTons": "41.2",
    "submissionStatus": "Flagged",
    "timestamp": "2026-07-02T14:30:00.000Z"
  },
  {
    "id": "REC-003",
    "fieldName": "Golden Plains Sector 4",
    "variety": "Snowden",
    "country": "USA",
    "vendorName": "Midwest Agri Services",
    "growerName": "Sarah Jenkins",
    "cropSeason": "2026",
    "fieldLocation": "41.8781, -87.6298",
    "region": "NA",
    "vendorContact": "+1-312-555-0143",
    "cipcApplied": "CIPC",
    "activeIngredientRate": "15.75",
    "irrigationType": "Flood",
    "nApplied": "22.40",
    "nTotal": "3.50",
    "pTotal": "1.75",
    "kTotal": "2.10",
    "vrtUsed": "Yes",
    "fertilizerType": "Mineral NPK",
    "fertilizerNature": "Mineral",
    "nitrogenAnalysis": "24.0",
    "ammoniaPercentage": "40.0",
    "nitricPercentage": "40.0",
    "ureaPercentage": "20.0",
    "phosphateAnalysis": "12.0",
    "potassiumAnalysis": "12.0",
    "applicationRate": "200.0",
    "applicationMethod": "Banding",
    "emissionsInhibitors": "Yes",
    "applicationDate": "2026-04-01",
    "agronomistName": "Jane Smith",
    "moisturePercentage": "13.8",
    "defectRate": "1.8",
    "yieldTons": "48.9",
    "submissionStatus": "Approved",
    "timestamp": "2026-07-04T09:15:00.000Z"
  },
  {
    "id": "REC-004",
    "fieldName": "Pampa Verde South",
    "variety": "Frito-Lay Proprietary",
    "country": "ARG",
    "vendorName": "Pampa Farms SA",
    "growerName": "Juan Gomez",
    "cropSeason": "2026",
    "fieldLocation": "-34.6037, -58.3816",
    "region": "LATAM",
    "vendorContact": "+54-11-4820-2918",
    "cipcApplied": "Other",
    "activeIngredientRate": "8.40",
    "irrigationType": "Rainfed",
    "nApplied": "18.20",
    "nTotal": "1.90",
    "pTotal": "0.95",
    "kTotal": "1.40",
    "vrtUsed": "No",
    "fertilizerType": "Urea",
    "fertilizerNature": "Mineral",
    "nitrogenAnalysis": "46.0",
    "ammoniaPercentage": "0.0",
    "nitricPercentage": "0.0",
    "ureaPercentage": "100.0",
    "phosphateAnalysis": "0.0",
    "potassiumAnalysis": "0.0",
    "applicationRate": "120.0",
    "applicationMethod": "Broadcast",
    "emissionsInhibitors": "No",
    "applicationDate": "2026-03-22",
    "agronomistName": "Carlos Garcia",
    "moisturePercentage": "21.5",
    "defectRate": "12.3",
    "yieldTons": "22.1",
    "submissionStatus": "Pending",
    "timestamp": "2026-07-05T16:45:00.000Z"
  },
  {
    "id": "REC-005",
    "fieldName": "Ganges Basin Farm C",
    "variety": "Low Glycemic",
    "country": "IND",
    "vendorName": "Ganges Valley Growers",
    "growerName": "Amit Sharma",
    "cropSeason": "2026",
    "fieldLocation": "25.3176, 82.9739",
    "region": "AMESA",
    "vendorContact": "+91-9988776655",
    "cipcApplied": "CIPC",
    "activeIngredientRate": "11.20",
    "irrigationType": "Drip",
    "nApplied": "27.50",
    "nTotal": "3.20",
    "pTotal": "1.60",
    "kTotal": "2.40",
    "vrtUsed": "Yes",
    "fertilizerType": "Mineral NPK",
    "fertilizerNature": "Mineral",
    "nitrogenAnalysis": "20.0",
    "ammoniaPercentage": "38.9",
    "nitricPercentage": "30.1",
    "ureaPercentage": "31.0",
    "phosphateAnalysis": "15.0",
    "potassiumAnalysis": "15.0",
    "applicationRate": "160.0",
    "applicationMethod": "Drip",
    "emissionsInhibitors": "Yes",
    "applicationDate": "2026-03-12",
    "agronomistName": "Sujit Kumar",
    "moisturePercentage": "15.1",
    "defectRate": "3.4",
    "yieldTons": "38.7",
    "submissionStatus": "Approved",
    "timestamp": "2026-07-06T11:20:00.000Z"
  }
]